error_code/__init__.py
error_code/error_code_info.py
error_code-0.0.11.dist-info/METADATA
error_code-0.0.11.dist-info/WHEEL
error_code-0.0.11.dist-info/top_level.txt
error_code-0.0.11.dist-info/RECORD
